mergething/__init__.py
mergething/cli.py
mergething/ipython.py
mergething-0.1.1.dist-info/METADATA
mergething-0.1.1.dist-info/WHEEL
mergething-0.1.1.dist-info/entry_points.txt
mergething-0.1.1.dist-info/licenses/LICENSE.txt
mergething-0.1.1.dist-info/RECORD
