Metadata-Version: 2.3
Name: mergething
Version: 0.1.1
Summary: App over syncthing that takes care merging things
Project-URL: Homepage, https://github.com/drorspei/mergething
Project-URL: Repository, https://github.com/drorspei/mergething
Author-email: Dror Speiser <drorspei@gmail.com>
License: MIT
License-File: LICENSE.txt
Keywords: history,ipython,jupyter,merge,sync,syncthing
Classifier: Development Status :: 4 - Beta
Classifier: Intended Audience :: Developers
Classifier: License :: OSI Approved :: MIT License
Classifier: Operating System :: OS Independent
Classifier: Programming Language :: Python :: 3
Classifier: Programming Language :: Python :: 3.8
Classifier: Programming Language :: Python :: 3.9
Classifier: Programming Language :: Python :: 3.10
Classifier: Programming Language :: Python :: 3.11
Classifier: Programming Language :: Python :: 3.12
Classifier: Topic :: Software Development :: Libraries :: Python Modules
Classifier: Topic :: System :: Systems Administration
Requires-Python: >=3.8
